textual_pax/DFTable.py
textual_pax/E700VaultLabels.py
textual_pax/SingleTermDetailsScreen.py
textual_pax/TI_Input.py
textual_pax/WarrantyChecker.py
textual_pax/__about__.py
textual_pax/__init__.py
textual_pax/commands.py
textual_pax/confmscn.py
textual_pax/entry_points.py
textual_pax/functionsScreen.py
textual_pax/notasync.py
textual_pax/paxModule.py
textual_pax/paxStoreChecker.py
textual_pax/replace_terminal_screen.py
textual_pax/revertpaxmodule.py
textual_pax/scan_qr.py
textual_pax/scan_serials.py
textual_pax/scan_v2.py
textual_pax/serialNoValidator.py
textual_pax/singleTermScreen.py
textual_pax/singleTerminal.py
textual_pax/textual_file_selector.py
textual_pax/ti_labels_iccid.py
textual_pax/tui_exceptions.py
textual_pax/css_lib/cofirm_screen.tcss
textual_pax/css_lib/combining_layouts.tcss
textual_pax/css_lib/group_gunctions.tcss
textual_pax/css_lib/scan_or_import_screen.tcss
textual_pax/css_lib/screen01.tcss
textual_pax/css_lib/singleTermDetails.tcss
textual_pax/css_lib/welcom.tcss
textual_pax-0.1.96.dist-info/METADATA
textual_pax-0.1.96.dist-info/WHEEL
textual_pax-0.1.96.dist-info/entry_points.txt
textual_pax-0.1.96.dist-info/licenses/LICENSE.txt
textual_pax-0.1.96.dist-info/RECORD
