Metadata-Version: 2.3
Name: textual-pax
Version: 0.1.96
Author-email: Scott <fake@fake.com>
License-Expression: MIT
License-File: LICENSE.txt
Classifier: Development Status :: 4 - Beta
Classifier: Programming Language :: Python
Classifier: Programming Language :: Python :: 3.8
Classifier: Programming Language :: Python :: 3.9
Classifier: Programming Language :: Python :: 3.10
Classifier: Programming Language :: Python :: 3.11
Classifier: Programming Language :: Python :: 3.12
Classifier: Programming Language :: Python :: Implementation :: CPython
Classifier: Programming Language :: Python :: Implementation :: PyPy
Requires-Python: >=3.8
Requires-Dist: aiohttp
Requires-Dist: pandas
Requires-Dist: reportlab
Requires-Dist: reportlab-qrcode
Requires-Dist: requests
Requires-Dist: textual
